talentro/__init__.py
talentro/billing/__init__.py
talentro/billing/dataclasses.py
talentro/billing/models.py
talentro/campaigns/__init__.py
talentro/campaigns/dataclasses.py
talentro/campaigns/models.py
talentro/candidates/__init__.py
talentro/candidates/dataclasses.py
talentro/constants.py
talentro/event.py
talentro/exceptions.py
talentro/general/__init__.py
talentro/general/dataclasses.py
talentro/general/models.py
talentro/iam/__init__.py
talentro/iam/dataclasses.py
talentro/iam/models.py
talentro/iam/types.py
talentro/integrations/__init__.py
talentro/integrations/dataclasses.py
talentro/integrations/models.py
talentro/util/__init__.py
talentro/util/enum.py
talentro/vacancies/__init__.py
talentro/vacancies/dataclasses.py
talentro/vacancies/models.py
talentro_definitions-0.12.3.dist-info/METADATA
talentro_definitions-0.12.3.dist-info/WHEEL
talentro_definitions-0.12.3.dist-info/RECORD
