Metadata-Version: 2.3
Name: talentro-definitions
Version: 0.12.3
Summary: This package contains all models and data structures for Talentro
License: Proprietary
Author: Emiel van Essen
Author-email: emiel@marksmen.nl
Requires-Python: >=3.13
Classifier: License :: Other/Proprietary License
Classifier: Programming Language :: Python :: 3
Classifier: Programming Language :: Python :: 3.13
Requires-Dist: fastapi (>=0.116.0,<0.117.0)
Requires-Dist: sqlalchemy (>=2.0.38,<3.0.0)
Requires-Dist: sqlmodel (>=0.0.24,<0.0.25)
